fastllm/__init__.py
fastllm/base.py
fastllm/utils.py
fastllm-0.2.1.dist-info/LICENSE
fastllm-0.2.1.dist-info/METADATA
fastllm-0.2.1.dist-info/WHEEL
fastllm-0.2.1.dist-info/RECORD
