Metadata-Version: 2.1
Name: fastllm
Version: 0.2.1
Summary: Fast and easy wrapper around LLMs.
Home-page: https://github.com/clemens33/fastllm
License: Apache-2.0
Keywords: agents,chatbots,openai,llm,ai
Author: Clemens Kriechbaumer
Author-email: clemens.kriechbaumer@gmail.com
Requires-Python: >=3.10,<4.0
Classifier: Development Status :: 2 - Pre-Alpha
Classifier: License :: OSI Approved :: Apache Software License
Classifier: Programming Language :: Python :: 3
Classifier: Programming Language :: Python :: 3.10
Classifier: Programming Language :: Python :: 3.11
Classifier: Programming Language :: Python :: 3.12
Requires-Dist: backoff (>=2.2.1,<3.0.0)
Requires-Dist: beautifulsoup4[samples] (>=4.12.2,<5.0.0)
Requires-Dist: exrex (>=0.11.0,<0.12.0)
Requires-Dist: jinja2 (>=3.1.2,<4.0.0)
Requires-Dist: jsonschema (>=4.20.0,<5.0.0)
Requires-Dist: openai (>=1.5.0,<2.0.0)
Requires-Dist: requests[samples] (>=2.31.0,<3.0.0)
Requires-Dist: tiktoken (>=0.5.2,<0.6.0)
Project-URL: Repository, https://github.com/clemens33/fastllm
